<?xml version="1.0" encoding="utf-8" standalone="yes" ?>
<T3locallang>
  <meta type="array">
    <type>database</type>
    <description></description>
  </meta>
  <data type="array">
    <languageKey index="default" type="array">
      <label index="email_label">subscribe to newsletter</label>
      <label index="submit">subscribe</label>
      <label index="already-listed">Seems like you're already on the list :-)</label>
      <label index="invalid-email">I don't think that's a valid email address</label>
      <label index="default-email-used">John is already getting enough mail. Why not sign up with your own address? :)</label>
      <label index="response-error">An error occurred while I tried to sign you up. Sorry :(</label>
      <label index="response-success">Subscribed - look for the confirmation email!</label>

    </languageKey>
    <languageKey index="de" type="array">
      <label index="email_label">Newsletter abonnieren</label>
      <label index="submit">anmelden</label>
      <label index="already-listed">Sie stehen schon auf der Liste :-)</label>
      <label index="invalid-email">Das ist aber keine gültige Email-Adresse</label>
      <label index="default-email-used">John bekommt schon genug Emails. Tragen Sie doch Ihre Adresse ein :)</label>
      <label index="response-error">Fehler bei der Anmeldung. Sorry :(</label>
      <label index="response-success">Angemeldet - schauen Sie in Ihr Postfach!</label>

    </languageKey>
  </data>
</T3locallang>